{
  "video_id": "k8XlCBCZ8FM",
  "url": "https://www.youtube.com/watch?v=k8XlCBCZ8FM",
  "title": "Amazon KDP Niche & Keyword Research 101 | Step-by-Step Guide + LIVE Analysis",
  "channel": "Driven Publishers",
  "publish_date": "20240618",
  "duration_seconds": 1672,
  "view_count": 5850,
  "description": "\ud83d\udd34 Stop Relying on Outdated Strategies & Get Direct Advice From Top Level-Publishers Who Have Their Finger on the Pulse\n \u25ba https://elite.drivenpublishers.com/application\n\n\ud83d\udc47 Join 2.2K Other Driven Publishers in our FREE Amazon KDP Skool Community & Connect With Us:\nhttps://www.skool.com/self-publishing-entrepreneurs-9850\nConnect with fellow self-publishers, share insights, and flourish your Amazon KDP Business. A collaborative network to inspire and empower each other.\n\nMy favorite tool for keyword research: https://bookbeam.io/?ref=340 \nUse promo code DRIVEN10 to get 10% off for the yearly plan or DRIVEN50 to get 50% off on the first month. The link above is an affiliate link. If you buy through it and apply any of the promo codes, you get cool stuff for a better price, and help support the creation of more videos.\n\nDiscover powerful strategies to master niche research for your book and uncover profitable keywords for your Amazon KDP business!\n\nMy favorite tool for keyword research: htt",
  "tags": [
    "sean dollwet",
    "barry kdp",
    "amazon kdp business",
    "amazon kdp tips",
    "amazon kdp publishing",
    "kindle publishing",
    "kindle direct publishing",
    "self-publishing",
    "amazon kdp niche research",
    "amazon kdp finding niches",
    "amazon kdp keyword research",
    "amazon kdp ads",
    "amazon kdp get more traffic",
    "amazon kdp best book",
    "amazon kdp algorithm",
    "how does the amazon algorithm work",
    "amazon kdp higher ctr",
    "amazon ctr boost",
    "how to make sales amazon kdp",
    "amazon kdp tips for selling",
    "how to get high ctr"
  ],
  "transcript_lang": "auto",
  "transcript_word_count": 4120,
  "collected_at": "2026-02-18T12:29:35.777066"
}