{
  "video_id": "XQLGOxprmIs",
  "url": "https://www.youtube.com/watch?v=XQLGOxprmIs",
  "title": "Beginners Guide to KDP Niche Research",
  "channel": "Austin Sunday",
  "publish_date": "20251008",
  "duration_seconds": 758,
  "view_count": 2063,
  "description": "Are you struggling to make sales on Amazon KDP and wondering, \u201cWhy isn\u2019t my book selling?\u201d \ud83e\udd14 You\u2019re not alone! In this video, I break down 5 powerful ways to know if a niche is profitable or not \u2014 so you can stop wasting time on unprofitable niches and start publishing books that actually sell! \ud83d\udcda\ud83d\udcb0\n\nYou\u2019ll learn:\n\u2705 How to research demand before publishing\n\u2705 The signs of a saturated or dead niche\n\u2705 What to check on Amazon before choosing your next keyword\n\u2705 How to analyze competitors the smart way\n\u2705 Tools and tricks to confirm if your niche can make consistent sales\n\nWhether you\u2019re a beginner on Amazon KDP or you\u2019ve been publishing for a while with no results, this video will help you understand what really makes a niche profitable \u2014 and how to avoid common mistakes that stop your books from selling.",
  "tags": [
    "amazon kdp niche research",
    "niche research amazon",
    "niche research on amazon",
    "amazon kdp niche reserch for low content books",
    "niche research for kdp",
    "amazon kdp keyword research",
    "kdp no content niche research",
    "amazon kdp new niches",
    "selling books on amazon kdp",
    "how to start selling on amazon kdp",
    "selling digital products on amazon kdp",
    "how to sell books on amazon",
    "5 tips to sell amazon kdp books fast",
    "amazon kdp low content books",
    "self publishing on amazon kdp"
  ],
  "transcript_lang": "auto",
  "transcript_word_count": 2915,
  "collected_at": "2026-02-18T02:55:18.697846"
}