{
  "video_id": "j8BS_SDzTsE",
  "url": "https://www.youtube.com/watch?v=j8BS_SDzTsE",
  "title": "LOW COMPETITION AMAZON KDP NICHE! Free KeyWords + Title Idea!",
  "channel": "MK Publishing",
  "publish_date": "20220929",
  "duration_seconds": 805,
  "view_count": 1370,
  "description": "\u25ac \ud83d\udee0\ufe0f Tools I use for my Amazon KDP Business \u25ac\n\nSellersprite \u2013 Research tool for only $32/month (35% discount)\nhttps://www.sellersprite.com/affiliate/MKPublishing\n\nHelium10 \u2013 Up to 30% discount for 12 months!\nhttps://helium10.pxf.io/nX3q96\n\nGemsy \u2013 Collect reviews for your KDP books (30% discount \u2013 Code: MATTHIAS30)\nhttps://gemsy.io/?via=mkpublishing\n\nBookBolt \u2013 All-in-one tool for mid-content books (20% discount \u2013 Code: MKPublishing)\nhttps://bookbolt.io/3033.html\n\nPublisherRocket \u2013 Keyword research for KDP\nhttps://mkdigitalpublishing--rocket.thrivecart.com/publisher-rocket/\n\nCreative Fabrica \u2013 Thousands of graphics for KDP\nhttps://www.creativefabrica.com/ref/1751850/\n\nPIXELFY \u2013 Save 5% with code: MK\nhttps://pixelfy.me/?aff=29186\n\n(Note: These are paid affiliate links. You don\u2019t pay anything extra by using them.)\n\n\u25ac In today's Video \u25ac\n\nIn today's video I show you an amazon kdp evergreen niche with little competition where you can earn up to $3000 per month. In this video you will learn ",
  "tags": [
    "amazon kdp income reports",
    "amazon kdp beginner",
    "amazon kdp low content",
    "amazon kdp no content",
    "amazon kdp high content",
    "amazon kdp revenue",
    "amazon kdp earnings",
    "amazon kdp tutorial",
    "amazon kdp business",
    "amazon kdp low content business",
    "amazon kdp no content business",
    "amazon kdp royalties",
    "amazon kdp niche research",
    "amazon kdp niche",
    "amazon kdp interior",
    "amazon kdp cover",
    "amazon kdp creating cover",
    "amazon kdp free tools",
    "kdp niche ideas",
    "amazon kdp low competition"
  ],
  "transcript_lang": "manual",
  "transcript_word_count": 2046,
  "collected_at": "2026-02-18T19:30:30.401579"
}