{
  "video_id": "MrMzMMKWxnA",
  "url": "https://www.youtube.com/watch?v=MrMzMMKWxnA",
  "title": "Before You Buy Publisher Rocket in 2026\u2026 Watch This",
  "channel": "Krista Brea - KDP Self Publishing ",
  "publish_date": "20260104",
  "duration_seconds": 313,
  "view_count": 380,
  "description": "\ud83d\udc47 Publisher Rocket affiliate link (mentioned in the video):\nhttps://publisherrocket.cartknox.com/buy-rocket?aff=47Before You Buy \n\nThinking about buying Publisher Rocket but not sure if it\u2019s worth it? In this video, I break down the biggest objections people have before purchasing Publisher Rocket and give you an honest, experience-based review from a self-published author who actually uses it.\n\nI\u2019ve published many books on Amazon, and the titles that have performed the best all have one thing in common: I used Publisher Rocket to do keyword research before writing the manuscript. This tool helps you identify what readers are already searching for, avoid oversaturated niches, and position your book for organic discovery on Amazon.\n\nIn this video, you\u2019ll learn:\n\u2013 What Publisher Rocket does (and what it doesn\u2019t)\n\u2013 Common mistakes new authors make with Amazon keyword research\n\u2013 Why writing a book without validating demand first is risky\n\u2013 How Publisher Rocket fits into a smart self-publis",
  "tags": [],
  "transcript_lang": "auto",
  "transcript_word_count": 918,
  "collected_at": "2026-02-18T19:38:33.955705"
}