{
  "video_id": "3mTq-zgxlaQ",
  "url": "https://www.youtube.com/watch?v=3mTq-zgxlaQ",
  "title": "Top 3 Low Competition High Demand Keywords KDP Low Content Books #kdp #kdpkeywords",
  "channel": "Passive Income With Nora",
  "publish_date": "20230325",
  "duration_seconds": 548,
  "view_count": 463,
  "description": "kdp low content books,low content book publishing,low content books,low content books kdp,low content books amazon,low content publishing,low content kdp,no content books,amazon kdp low content books,kdp low content,low content book publishing kdp,low content publishing kdp,no content book publishing,kdp low content books tutorial,low content,kdp low content publishing,medium content books,selling low content books,sell more low content books",
  "tags": [
    "kdp low content books",
    "low content book publishing",
    "low content books",
    "low content books kdp",
    "low content books amazon",
    "low content publishing",
    "low content kdp",
    "no content books",
    "amazon kdp low content books",
    "kdp low content",
    "low content book publishing kdp",
    "low content publishing kdp",
    "no content book publishing",
    "kdp low content books tutorial",
    "low content",
    "kdp low content publishing",
    "medium content books",
    "selling low content books",
    "sell more low content books"
  ],
  "transcript_lang": "auto",
  "transcript_word_count": 1386,
  "collected_at": "2026-02-18T19:31:36.083462"
}